{
	"version": "1.0.0",
	"sampleId": "secretmanager_v1_secretmanagerservice_secretversion_get",
	"title": "Get Secret Version Metadata",
	"description": "Retrieves the metadata for a specific secret version. This demonstrates how to fetch information about a secret version without accessing its payload.",
	"dateCreated": "2026-02-22T21:31:15.339Z",
	"sampleType": "rpc",
	"objective": {
		"narrative": "Get a secret version and verify its state within a Global environment.",
		"products": [
			"secretmanager"
		],
		"authentication": "adc"
	},
	"extended": {
		"api": "secretmanager.googleapis.com",
		"method": "GetSecretVersion",
		"service_version": "v1",
		"parent_resource": "projects/{project}",
		"client_class": "SecretManagerServiceClient",
		"library_method": "getSecretVersion",
		"is_async": true,
		"scenarioId": "google.cloud.secretmanager_v1.SecretManagerMeta.GetSecretVersion",
		"branch_features": {},
		"verb": "get",
		"resource": "secret version",
		"standard": true,
		"transport": {
			"type": "GLOBAL"
		},
		"storage": {
			"topology_type": "GLOBAL",
			"locations": []
		},
		"fixtures": [
			{
				"ref": "secretmanager_secret",
				"output_mapping": {
					"version_name": "name"
				}
			}
		],
		"parameters": [
			{
				"name": "name",
				"source": "secretmanager_secret.version_name"
			}
		]
	},
	"regionTags": [
		{
			"name": "secretmanager_v1_secretmanagerservice_secretversion_get",
			"title": "Get Secret Version Metadata",
			"description": "Retrieves the metadata for a specific secret version. This demonstrates how to fetch information about a secret version without accessing its payload."
		},
		{
			"name": "secretmanager_secretmanagerservice_secretversion_get"
		}
	],
	"instances": [
		{
			"name": "NODEJS-@google-cloud/secret-manager",
			"categories": {
				"language": "NODEJS"
			},
			"initialCommitAuthorType": "ai_assisted_human_reviewed"
		},
		{
			"name": "PYTHON-google-cloud-secret-manager",
			"categories": {
				"language": "PYTHON"
			},
			"initialCommitAuthorType": "ai_assisted_human_reviewed"
		}
	]
}